typingchecker/__init__.py
typingchecker/typingchecker_function.py
typingchecker-0.1.11.dist-info/LICENSE
typingchecker-0.1.11.dist-info/METADATA
typingchecker-0.1.11.dist-info/WHEEL
typingchecker-0.1.11.dist-info/top_level.txt
typingchecker-0.1.11.dist-info/RECORD
