Metadata-Version: 2.1
Name: typingchecker
Version: 0.1.11
Summary: A tool for checking Python type annotations
Author-email: Oliver Maith <oliver_maith@gmx.de>
License: MIT License
Project-URL: Source, https://github.com/Olmai/typingchecker
Keywords: typing
Classifier: License :: OSI Approved :: MIT License
Classifier: Programming Language :: Python
Classifier: Programming Language :: Python :: 3
Requires-Python: >=3.10
License-File: LICENSE
